nuclear/__init__.py
nuclear/bitmatrix.py
nuclear/confread.py
nuclear/hotspots.py
nuclear/minimizer.py
nuclear/nuclear.py
nuclear/oligogen.py
nuclear/sampling.py
nuclear/skeleton.py
nuclear_toppar/par_all27_prot_na_scal3.prm
nuclear_toppar/par_all36_carb.prm
nuclear_toppar/par_all36_cgenff.prm
nuclear_toppar/par_all36_na.prm
nuclear_toppar/par_all36_prot.prm
nuclear_toppar/top_all27_prot_na_scal3.rtf
nuclear_toppar/top_all36_carb.rtf
nuclear_toppar/top_all36_cgenff.rtf
nuclear_toppar/top_all36_na.rtf
nuclear_toppar/top_all36_prot.rtf
nuclear_toppar/toppar_all36_na_model.str
nuclear_toppar/toppar_all36_na_modifications.str
nuclear_toppar/toppar_all36_na_rna_modified.str
nuclear_toppar/toppar_water_ions.str
nuklear-0.0.1.dist-info/LICENSE.txt
nuklear-0.0.1.dist-info/METADATA
nuklear-0.0.1.dist-info/WHEEL
nuklear-0.0.1.dist-info/entry_points.txt
nuklear-0.0.1.dist-info/top_level.txt
nuklear-0.0.1.dist-info/RECORD
