Metadata-Version: 2.1
Name: nuklear
Version: 0.0.1
Summary: NUCLeotide AssembleR
Home-page: https://github.com/rglez/nuclear/
Author: Roy Gonzalez
Author-email: roy.gonzalez.aleman@gmail.com
License: MIT
Project-URL: Source, https://github.com/rglez/nuclear/
Project-URL: Changelog, https://github.com/rglez/nuclear/blob/main/CHANGELOG.md
Project-URL: Tracker, https://github.com/rglez/nuclear/issues/
Platform: any
Classifier: Development Status :: 4 - Beta
Classifier: Programming Language :: Python
License-File: LICENSE.txt
Requires-Dist: importlib-metadata ; python_version < "3.9"
Provides-Extra: testing
Requires-Dist: setuptools ; extra == 'testing'
Requires-Dist: pytest ; extra == 'testing'
Requires-Dist: pytest-cov ; extra == 'testing'
